wl_utilities/__init__.py
wl_utilities/__version__.py
wl_utilities/misc/__init__.py
wl_utilities/spectrum/__init__.py
wl_utilities/spectrum/binning.py
wl_utilities/spectrum/cross_correlation.py
wl_utilities/spectrum/skylines.py
wl_utilities/stats/__init__.py
wl_utilities/stats/noiseprop.py
wl_utilities-2022.0.4.dist-info/METADATA
wl_utilities-2022.0.4.dist-info/WHEEL
wl_utilities-2022.0.4.dist-info/top_level.txt
wl_utilities-2022.0.4.dist-info/RECORD
