Metadata-Version: 2.1
Name: wl-utilities
Version: 2022.0.4
Summary: Utility code to perform QAG and SV analysis
Home-page: https://github.com/WEAVE-LOFAR/wl-utilities
Author: philastrophist
Author-email: shaun.c.read@gmail.com
License: MIT
Platform: UNKNOWN
Classifier: License :: OSI Approved :: MIT License
Classifier: Programming Language :: Python
Classifier: Programming Language :: Python :: 3
Classifier: Programming Language :: Python :: 3.7
Classifier: Programming Language :: Python :: Implementation :: CPython
Classifier: Programming Language :: Python :: Implementation :: PyPy
Requires-Dist: astropy
Requires-Dist: networkx
Requires-Dist: numpy
Requires-Dist: tqdm
Requires-Dist: matplotlib
Requires-Dist: jupyter
Requires-Dist: notebook
Requires-Dist: ipython
Requires-Dist: scipy
Requires-Dist: lmfit
